CBianchengyuyanYuMianxiangduixiangJichuJingjianJiaochengJinxuliang/README.md
CBianchengyuyanYuMianxiangduixiangJichuJingjianJiaochengJinxuliang/__init__.py
CBianchengyuyanYuMianxiangduixiangJichuJingjianJiaochengJinxuliang/__main__.py
CBianchengyuyanYuMianxiangduixiangJichuJingjianJiaochengJinxuliang/file.pdf
CBianchengyuyanYuMianxiangduixiangJichuJingjianJiaochengJinxuliang/index.html
c_bianchengyuyan_yu_mianxiangduixiang_jichu_jingjian_jiaocheng_jinxuliang-2024.3.2.0.dist-info/METADATA
c_bianchengyuyan_yu_mianxiangduixiang_jichu_jingjian_jiaocheng_jinxuliang-2024.3.2.0.dist-info/WHEEL
c_bianchengyuyan_yu_mianxiangduixiang_jichu_jingjian_jiaocheng_jinxuliang-2024.3.2.0.dist-info/entry_points.txt
c_bianchengyuyan_yu_mianxiangduixiang_jichu_jingjian_jiaocheng_jinxuliang-2024.3.2.0.dist-info/top_level.txt
c_bianchengyuyan_yu_mianxiangduixiang_jichu_jingjian_jiaocheng_jinxuliang-2024.3.2.0.dist-info/RECORD
